utility_logger/__init__.py
utility_logger/logger_jm.py
Utility_logger_jma-0.0.1.dist-info/LICENSE
Utility_logger_jma-0.0.1.dist-info/METADATA
Utility_logger_jma-0.0.1.dist-info/WHEEL
Utility_logger_jma-0.0.1.dist-info/top_level.txt
Utility_logger_jma-0.0.1.dist-info/RECORD
