Metadata-Version: 2.1
Name: Utility-logger-jma
Version: 0.0.1
Summary: A package for logging convenience
Home-page: https://github.com/jm-h10/utility_jma/utility_logger
Author: Jinghan Ma
Author-email: jinghan.m@helium10.com
License: UNKNOWN
Project-URL: Bug Tracker, https://github.com/jm-h10/utility_jma/utility_logger
Platform: UNKNOWN
Classifier: Programming Language :: Python :: 3
Classifier: License :: OSI Approved :: MIT License
Classifier: Operating System :: OS Independent
Requires-Python: >=3.6
